variant_repack.py
variant_repack-0.0.0.dist-info/WHEEL
variant_repack-0.0.0.dist-info/METADATA
variant_repack-0.0.0.dist-info/RECORD
