Metadata-Version: 2.4
Name: variant-repack
Version: 0.0.0
Summary: A library that provides help to Python Wheel into Wheel Variants.
Author-email: Jonathan Dekhtiar <jonathan@dekhtiar.com>
Maintainer-email: Jonathan Dekhtiar <jonathan@dekhtiar.com>
Requires-Python: >=3.10
